LICENSE
README.md
ogn/__init__.py
ogn/client/__init__.py
ogn/client/client.py
ogn/client/settings.py
ogn/ddb/__init__.py
ogn/ddb/utils.py
ogn/parser/__init__.py
ogn/parser/aprs_comment/__init__.py
ogn/parser/aprs_comment/base.py
ogn/parser/aprs_comment/fanet_parser.py
ogn/parser/aprs_comment/flarm_parser.py
ogn/parser/aprs_comment/generic_parser.py
ogn/parser/aprs_comment/inreach_parser.py
ogn/parser/aprs_comment/lt24_parser.py
ogn/parser/aprs_comment/microtrak_parser.py
ogn/parser/aprs_comment/naviter_parser.py
ogn/parser/aprs_comment/ogn_parser.py
ogn/parser/aprs_comment/receiver_parser.py
ogn/parser/aprs_comment/safesky_parser.py
ogn/parser/aprs_comment/skylines_parser.py
ogn/parser/aprs_comment/spider_parser.py
ogn/parser/aprs_comment/spot_parser.py
ogn/parser/aprs_comment/tracker_parser.py
ogn/parser/exceptions.py
ogn/parser/parse.py
ogn/parser/pattern.py
ogn/parser/telnet_parser.py
ogn/parser/utils.py
python_ogn_client-1.3.0.dist-info/LICENSE
python_ogn_client-1.3.0.dist-info/METADATA
python_ogn_client-1.3.0.dist-info/WHEEL
python_ogn_client-1.3.0.dist-info/RECORD
