Metadata-Version: 2.3
Name: python-ogn-client
Version: 1.3.0
Summary: A python module for the Open Glider Network
License: AGPL-3.0-only
Keywords: gliding,ogn
Author: Konstantin Gründger
Author-email: konstantin.gruendger@web.de
Maintainer: Konstantin Gründger
Maintainer-email: konstantin.gruendger@web.de
Requires-Python: >=3.9
Classifier: Development Status :: 4 - Beta
Classifier: Intended Audience :: Developers
Classifier: Intended Audience :: Science/Research
Classifier: Topic :: Scientific/Engineering :: GIS
Classifier: License :: OSI Approved :: GNU Affero General Public License v3
Classifier: Programming Language :: Python :: 3 :: Only
Requires-Dist: requests (>=2.32.3,<3.0.0)
Project-URL: Repository, https://github.com/glidernet/python-ogn-client
